groepszoeker.py
groepszoeker-0.1.1.dist-info/LICENSE
groepszoeker-0.1.1.dist-info/WHEEL
groepszoeker-0.1.1.dist-info/METADATA
groepszoeker-0.1.1.dist-info/RECORD
