Metadata-Version: 2.1
Name: groepszoeker
Version: 0.1.1
Summary: A library for finding sub-populations within a group of numerical values.
Home-page: https://gitlab.com/gmb/groepszoeker
License: MIT
Author: Graham Binns
Author-email: graham@outcoded.dev
Requires-Python: >=3.6.1,<4.0
Classifier: License :: OSI Approved :: MIT License
Classifier: Programming Language :: Python :: 3
Classifier: Programming Language :: Python :: 3.7
Classifier: Programming Language :: Python :: 3.8
Classifier: Programming Language :: Python :: 3.9
Project-URL: Repository, https://gitlab.com/gmb/groepszoeker.git
